{
  "whisper_path": "",
  "hy_path": "",
  "audio_file": "",
  "language": "pt",
  "terminology": [
    {
      "source": "Eco",
      "target": "Eco"
    },
    {
      "source": "Rush",
      "target": "Rush"
    },
    {
      "source": "Save",
      "target": "保枪"
    },
    {
      "source": "Major",
      "target": "Major"
    },
    {
      "source": "Site",
      "target": "包点"
    },
    {
      "source": "CT",
      "target": "CT"
    },
    {
      "source": "T",
      "target": "T"
    },
    {
      "source": "AWP",
      "target": "AWP"
    },
    {
      "source": "AK",
      "target": "AK"
    },
    {
      "source": "M4",
      "target": "M4"
    },
    {
      "source": "Molotov",
      "target": "火"
    },
    {
      "source": "Flash",
      "target": "闪光"
    },
    {
      "source": "Smoke",
      "target": "烟"
    },
    {
      "source": "Nuke",
      "target": "Nuke"
    },
    {
      "source": "Dust2",
      "target": "沙二"
    },
    {
      "source": "Inferno",
      "target": "炼狱小镇"
    },
    {
      "source": "Mirage",
      "target": "Mirage"
    }
  ],
  "translate_mode": "api",
  "whisper_device": "cuda",
  "siliconflow_api_key": "sk-nltjtbecttnyvzzlfrqpxaoyezkguwlsojgqhofnbmicprhf",
  "siliconflow_model": "tencent/Hunyuan-MT-7B"
}